dropchain_sdk/__init__.py
dropchain_sdk-0.8.0.dist-info/LICENSE.md
dropchain_sdk-0.8.0.dist-info/METADATA
dropchain_sdk-0.8.0.dist-info/WHEEL
dropchain_sdk-0.8.0.dist-info/top_level.txt
dropchain_sdk-0.8.0.dist-info/RECORD
