Metadata-Version: 2.1
Name: dropchain-sdk
Version: 0.8.0
Summary: Build robust web3 applications seamlessly using Python with existing frameworks.
Home-page: https://github.com/cRazink/py_dropchain_sdk
Author: DropChain Inc
Author-email: carter@dropchain.network
License: MIT
Platform: UNKNOWN
Requires-Python: >=3.8
Requires-Dist: requests
